Metadata-Version: 1.1
Name: pygments-style-goggles
Version: 0.1
Summary: pygments-style-goggles is a colorful style for pygments.
Home-page: https://github.com/jschaf/pygments-style-goggles
Author: Joe Schafer
Author-email: joe@jschaf.com
License: GPLv2
Download-URL: https://github.com/jschaf/pygments-style-goggles/tarball/v0.1
Keywords: pygments syntax highlighting
Platform: UNKNOWN
Classifier: Development Status :: 4 - Beta
Classifier: Intended Audience :: Developers
Classifier: Intended Audience :: End Users/Desktop
Classifier: Intended Audience :: System Administrators
Classifier: License :: OSI Approved :: BSD License
Classifier: Operating System :: OS Independent
Classifier: Programming Language :: Python
Classifier: Programming Language :: Python :: 2
Classifier: Programming Language :: Python :: 3
Classifier: Topic :: Text Processing :: Filters
